ifg/__init__.py
ifg/calculator.py
ifg/examples.py
ifg/metadata.py
ifg/units_converter.py
ifg/utils.py
ifg-2.2.3.dist-info/LICENSE.txt
ifg-2.2.3.dist-info/METADATA
ifg-2.2.3.dist-info/WHEEL
ifg-2.2.3.dist-info/RECORD
